gmailify/__init__.py
gmailify/__main__.py
gmailify-1.0.0.dist-info/LICENSE
gmailify-1.0.0.dist-info/METADATA
gmailify-1.0.0.dist-info/WHEEL
gmailify-1.0.0.dist-info/top_level.txt
gmailify-1.0.0.dist-info/RECORD
