Metadata-Version: 2.1
Name: gmailify
Version: 1.0.0
Summary: This tool validates if gmail addresses and corporate emails with google mail servers are valid without being authenticated. The default thread is 10 to avoid being rate limited.
Home-page: https://github.com/codedbrain/gmailify
Author: Santosh Bhandari
License: UNKNOWN
Project-URL: Bug Tracker, https://github.com/codedbrain/gmailify/issues
Platform: UNKNOWN
Classifier: Programming Language :: Python :: 3
Classifier: License :: OSI Approved :: MIT License
Classifier: Operating System :: OS Independent
Requires-Python: >=3.6
License-File: LICENSE
Requires-Dist: requests (>=2.26.0)
Requires-Dist: argparse (>=1.4.0)
